pyautoai/__init__.py
pyautoai/engine.py
pyautoai/io.py
pyautoai/metrics.py
pyautoai/models.py
pyautoai/preprocessing.py
pyautoai/utils.py
PyAutoAI-0.0.0.dist-info/LICENSE
PyAutoAI-0.0.0.dist-info/METADATA
PyAutoAI-0.0.0.dist-info/WHEEL
PyAutoAI-0.0.0.dist-info/top_level.txt
PyAutoAI-0.0.0.dist-info/RECORD
