Metadata-Version: 2.1
Name: PyAutoAI
Version: 0.0.0
Summary: An auto-ML/AI package
Home-page: https://github.com/chris.oleary/pyautoai
Author: Christian O'Leary
Author-email: pyautoai@gmail.com
License: UNKNOWN
Platform: UNKNOWN
Classifier: Programming Language :: Python :: 3
Classifier: License :: OSI Approved :: MIT License
Classifier: Operating System :: OS Independent
Requires-Python: >=3.6
Requires-Dist: numpy
Requires-Dist: setuptools
Requires-Dist: scikit-learn (>=0.22.0)
Requires-Dist: imbalanced-learn
Requires-Dist: statsmodels
Requires-Dist: scipy
Requires-Dist: pandas
Requires-Dist: joblib
